dbguard/__init__.py
dbguard/core.py
dbguard/exceptions.py
dbguard-0.1.0.dist-info/licenses/LICENSE
dbguard-0.1.0.dist-info/METADATA
dbguard-0.1.0.dist-info/WHEEL
dbguard-0.1.0.dist-info/top_level.txt
dbguard-0.1.0.dist-info/RECORD
